LICENSE
MANIFEST.in
README.md
setup.cfg
setup.py
subprocess_manager/__init__.py
subprocess_manager/assert_variable_type.py
subprocess_manager/nbstream_readerwriter.py
subprocess_manager/run_subprocess.py
subprocess_manager.egg-info/PKG-INFO
subprocess_manager.egg-info/SOURCES.txt
subprocess_manager.egg-info/dependency_links.txt
subprocess_manager.egg-info/pbr.json
subprocess_manager.egg-info/top_level.txt