Metadata-Version: 1.1
Name: subprocess-manager
Version: 0.1.1
Summary: Python Subprocess Manager
Home-page: https://github.com/agramian/subprocess-manager
Author: Abtin Gramian
Author-email: abtin.gramian@gmail.com
License: UNKNOWN
Download-URL: https://github.com/agramian/subprocess-manager/tarball/v0.1.1
Keywords: subprocess,daemon,timeout,process,spawning,non-blocking
Platform: UNKNOWN
